{
  "header": {
    "nav": {
      "home": "Главная",
      "about": "О нас",
      "services": "Услуги",
      "portfolio": "Портфолио",
      "contact": "Контакты"
    }
  },
  "hero": {
    "hello": "Привет, это я",
    "job_prefix": "И я ",
    "job_title": "Frontend Разработчик",
    "description": "Lorem ipsum dolor sit amet consectetur adipisicing elit. Vitae nulla libero labore exercitationem, iste iusto unde eos.",
    "download_btn": "Скачать CV"
  },
  "portfolio": {
    "title_part1": "Последние ",
    "title_part2": "Проекты",
    "projects": [
      { "title": "Веб Дизайн", "desc": "Идеальные фронтенд-решения для электронной коммерции и сайтов." },
      { "title": "Мобильное Приложение", "desc": "Компактное мобильное приложение на современном стеке." },
      { "title": "Панель Управления", "desc": "Быстрая и адаптивная система управления для админов." },
      { "title": "Доставка Еды", "desc": "Платформа для онлайн-заказа и управления службой доставки." },
      { "title": "Крипто Кошелек", "desc": "Безопасный веб-кошелек на основе технологий блокчейн." },
      { "title": "Сайт Портфолио", "desc": "Современный персональный сайт для разработчиков и дизайнеров." }
    ]
  },
  "contact": {
    "title_part1": "Связаться со ",
    "title_part2": "Мной!",
    "name": "Полное имя",
    "email": "Email адрес",
    "phone": "Номер телефона",
    "subject": "Тема письма",
    "message": "Ваше сообщение...",
    "btn": "Отправить",
    "success": "Ваше сообщение успешно отправлено!",
    "error": "Произошла ошибка. Повторите попытку."
  },
  "footer": {
    "rights": "Copyright © 2026 Codehal | Все права защищены."
  }
}